{
    "formula": "mult(cosh(mult(var_2, var_0), N(N, N)), neg(add(var_1, var_2), N(N, N)))",
    "formula_human_readable": "(cosh((var_2*var_0))*neg((var_1+var_2)))",
    "formula_depth": 4,
    "n_vars": 3,
    "n_consts": 0,
    "n_points": 100,
    "var_bound_dict": {
        "var_0": [
            -5.0,
            5.0
        ],
        "var_1": [
            -5.0,
            5.0
        ],
        "var_2": [
            -5.0,
            5.0
        ]
    },
    "const_value_dict": {},
    "meta_list": [
        "symmetric_var_0"
    ],
    "points": {
        "var_0": [
            0.15855,
            -2.2138,
            -2.27272,
            0.44997,
            2.15439,
            0.14998,
            1.52153,
            -2.14348,
            0.55798,
            4.27462,
            -0.82035,
            2.75884,
            -4.93529,
            -2.83448,
            -2.64898,
            3.80594,
            3.09395,
            1.85766,
            -4.6926,
            0.64464,
            2.62702,
            -3.98793,
            -1.62166,
            -1.77863,
            4.09569,
            1.99858,
            -0.69319,
            -3.3827,
            -0.67951,
            -0.9415,
            -4.41562,
            -1.08115,
            3.89976,
            -2.21638,
            1.91818,
            4.90786,
            3.53305,
            3.65627,
            0.80164,
            -4.73628,
            -2.50171,
            -0.04412,
            2.74607,
            -3.8289,
            0.34561,
            1.14185,
            -0.73035,
            2.90301,
            -4.97454,
            -1.99452,
            2.62523,
            -1.92613,
            -1.70485,
            -4.97957,
            -1.0899,
            3.85253,
            4.2675,
            -2.40248,
            -0.74763,
            -4.21474,
            1.36469,
            3.05868,
            0.33662,
            -1.69409,
            3.62769,
            -4.75985,
            -1.91282,
            -3.0783,
            2.93477,
            2.2222,
            -0.55913,
            2.98347,
            2.45772,
            1.51014,
            -0.60347,
            -2.61978,
            -4.60796,
            3.61626,
            -4.84124,
            -0.0574,
            3.45266,
            4.14737,
            -2.90787,
            0.48138,
            3.09211,
            -1.31982,
            4.55852,
            3.79439,
            1.56466,
            -2.01122,
            -1.9656,
            -2.6071,
            2.44045,
            1.51654,
            4.90597,
            2.90349,
            -1.04165,
            0.39486,
            -0.54075,
            0.45499
        ],
        "var_1": [
            2.03922,
            -2.61389,
            -0.32313,
            3.0137,
            -4.65559,
            -1.16495,
            2.27125,
            2.69136,
            4.4373,
            1.54676,
            -2.84446,
            4.1361,
            -0.54863,
            0.35715,
            3.15114,
            -1.63558,
            2.47202,
            -2.00866,
            -4.30739,
            1.49764,
            -3.89122,
            -2.35274,
            4.46416,
            3.73818,
            4.60067,
            -0.03953,
            -0.03296,
            2.92212,
            1.52226,
            -4.90487,
            -2.68558,
            -1.09633,
            -0.78973,
            2.53411,
            1.08311,
            -4.8511,
            4.69543,
            4.79804,
            -0.97994,
            4.41175,
            2.72874,
            0.23265,
            4.27985,
            -3.50983,
            1.74565,
            3.86802,
            -2.00531,
            -2.65097,
            -0.42796,
            -2.59,
            3.08332,
            -1.65593,
            -4.69539,
            -0.99682,
            -4.6694,
            1.80659,
            2.54061,
            -0.24895,
            -1.89895,
            -2.67044,
            1.34339,
            -3.87877,
            2.12088,
            4.00076,
            -0.57084,
            2.94079,
            4.62811,
            4.73567,
            0.65158,
            1.25423,
            3.18759,
            2.34709,
            -1.16468,
            0.2178,
            1.58849,
            4.92448,
            4.5998,
            -2.74933,
            2.85628,
            -4.02628,
            3.79961,
            3.22976,
            1.34729,
            -0.81665,
            -2.30584,
            -4.36295,
            -1.0961,
            4.39892,
            0.54059,
            0.33274,
            0.76596,
            -1.6509,
            -4.48149,
            1.44631,
            -3.65605,
            4.14828,
            2.98441,
            3.32421,
            3.25215,
            -1.10211
        ],
        "var_2": [
            4.24495,
            5.10991,
            -4.04369,
            -4.20171,
            -4.72993,
            2.21731,
            0.66869,
            -1.74307,
            -2.49115,
            -3.76167,
            -2.84417,
            -2.52247,
            -4.22562,
            0.7936,
            4.90664,
            -0.6523,
            1.70552,
            -3.10872,
            2.43378,
            -2.81111,
            2.7045,
            0.33274,
            1.08693,
            1.84317,
            -3.47109,
            4.70611,
            3.06648,
            -2.83652,
            -3.75511,
            -3.66455,
            4.95457,
            0.26317,
            -2.06991,
            2.47045,
            -4.05359,
            0.61876,
            -2.78116,
            -1.23825,
            -4.90143,
            -3.51057,
            -0.04103,
            -0.3294,
            -2.4617,
            0.45846,
            2.95931,
            4.62884,
            -0.76788,
            -0.0029,
            0.4409,
            -4.98252,
            -0.98639,
            4.05905,
            0.24526,
            1.03781,
            1.34671,
            1.75683,
            1.32278,
            1.66972,
            -3.58269,
            1.94838,
            -3.57435,
            -4.21509,
            -0.60968,
            3.1816,
            2.141,
            -3.69923,
            4.37753,
            -0.58142,
            -1.08511,
            -0.82976,
            -0.81026,
            -2.61031,
            3.24623,
            1.05263,
            -3.99291,
            -2.10961,
            3.70289,
            1.68264,
            -3.72501,
            -1.17131,
            -0.78419,
            4.76687,
            2.08467,
            4.11247,
            -0.2398,
            2.59843,
            0.78326,
            -4.40223,
            4.76618,
            3.3127,
            -0.92593,
            3.87411,
            -2.01878,
            -0.1434,
            4.51386,
            4.59491,
            -2.17458,
            1.2067,
            -2.74997,
            -1.45067
        ],
        "target": [
            -7.44577,
            -61837.07781,
            16729.1458,
            4.49958,
            152256.78319,
            -1.07782,
            -4.86737,
            -20.62738,
            -3.97197,
            962620.3942,
            32.66762,
            -870.09851,
            1055792.71426,
            -6.32115,
            -1322237.49674,
            13.18866,
            -498.71551,
            695.65992,
            95623.27214,
            4.39512,
            573.72084,
            4.16925,
            -16.00181,
            -79.37797,
            -1110831.04829,
            -29492.22342,
            -13.02406,
            -188.98238,
            15.34444,
            144.14254,
            -2440001.98527,
            0.9033,
            6224.31318,
            -736.67954,
            4033.97332,
            38.26801,
            -15066.90585,
            -131.59336,
            131.7482,
            -645096.76807,
            -2.65483,
            0.09669,
            -840.80386,
            9.19203,
            -7.37379,
            -658.12825,
            3.19687,
            2.86715,
            -0.03644,
            51454.16802,
            -13.50951,
            -2249.81142,
            4.55673,
            -4.98679,
            6.97953,
            -1116.59077,
            -667.07525,
            -45.61339,
            40.9898,
            1176.33265,
            122.22997,
            1031270.95699,
            -1.64483,
            -691.1422,
            -1429.1123,
            747486.55122,
            -21787.19569,
            -15.20822,
            4.72417,
            -1.52982,
            -2.4619,
            102.47968,
            -2717.62216,
            -3.33466,
            12.15531,
            -297.92097,
            -9284255.19041,
            184.94506,
            1021247.93577,
            5.52513,
            -19.65373,
            -8306104.31473,
            -668.34406,
            -11.55491,
            3.38791,
            26.8801,
            4.15578,
            -221850.45511,
            -4930.19769,
            -1336.45934,
            0.55046,
            -30848.0713,
            417.5822,
            -1.32681,
            -839954.46697,
            -1755806.17745,
            -3.9712,
            -5.12332,
            -1.30014,
            3.16864
        ]
    }
}