{
    "formula": "mult(mult(neg(var_0, N), neg(var_2, N)), cosh(gaussian(var_1, N), N(N, N)))",
    "formula_human_readable": "((neg(var_0)*neg(var_2))*cosh(gaussian(var_1)))",
    "formula_depth": 4,
    "n_vars": 3,
    "n_consts": 0,
    "n_points": 100,
    "var_bound_dict": {
        "var_0": [
            -5.0,
            5.0
        ],
        "var_1": [
            -5.0,
            5.0
        ],
        "var_2": [
            -5.0,
            5.0
        ]
    },
    "const_value_dict": {},
    "meta_list": [
        "symmetric_var_1"
    ],
    "points": {
        "var_0": [
            -2.20489,
            -0.93569,
            -1.90965,
            5.03756,
            3.82236,
            -3.54857,
            -0.6707,
            1.85992,
            3.56469,
            0.37106,
            0.19774,
            -1.70168,
            -4.22843,
            -3.44887,
            4.24141,
            4.61087,
            0.20594,
            2.97779,
            -0.48462,
            -1.43289,
            1.16001,
            3.77011,
            3.15781,
            -2.41719,
            -2.10688,
            -0.44865,
            1.2788,
            -2.56744,
            -0.89978,
            2.91794,
            -4.95755,
            4.54464,
            -2.88332,
            -1.33138,
            4.21561,
            -2.44907,
            4.39108,
            -3.93419,
            -1.3411,
            2.52501,
            1.54494,
            -2.73275,
            -0.37745,
            2.98296,
            -3.3297,
            -0.09523,
            -4.58945,
            4.04101,
            -0.47469,
            -0.07331,
            2.82059,
            -3.13169,
            2.11646,
            -0.79104,
            4.67843,
            -2.18365,
            0.5116,
            -2.79588,
            -1.28571,
            -1.92696,
            1.62042,
            1.07973,
            2.57602,
            0.99277,
            4.82233,
            -2.17517,
            2.42024,
            2.87075,
            2.59418,
            -0.6816,
            -4.12104,
            -2.03559,
            3.68124,
            -3.797,
            -3.90841,
            3.26615,
            2.62683,
            -0.21584,
            -1.49697,
            3.83439,
            1.95428,
            0.06293,
            -3.68455,
            3.07794,
            1.55552,
            -4.51857,
            -3.38752,
            4.06812,
            2.71233,
            1.40134,
            3.31148,
            -4.89355,
            1.96177,
            -4.57102,
            0.64319,
            -2.29404,
            4.51812,
            3.27581,
            -2.38635,
            -2.60798
        ],
        "var_1": [
            4.36908,
            -4.03181,
            -2.85464,
            -2.66297,
            2.96665,
            2.34053,
            3.53317,
            -2.98953,
            2.82997,
            -4.67591,
            -0.14629,
            3.73577,
            2.77172,
            3.49392,
            -1.46052,
            -3.21486,
            -3.59606,
            -1.03809,
            -0.87576,
            1.59294,
            -3.46887,
            -2.51851,
            2.20377,
            -1.69792,
            2.81973,
            -1.00264,
            2.76207,
            -2.39583,
            -2.26111,
            0.1285,
            3.92792,
            -3.29013,
            0.2697,
            -3.54047,
            3.21681,
            2.41788,
            0.76436,
            2.11711,
            1.76521,
            -0.44889,
            -4.16772,
            -3.87838,
            -1.80759,
            0.42652,
            3.13288,
            -5.06999,
            -0.832,
            3.21907,
            -1.41225,
            -0.78694,
            -2.87566,
            -2.25956,
            0.37253,
            3.62505,
            3.98315,
            -4.81369,
            3.69649,
            -0.94324,
            4.52827,
            -0.79004,
            -4.32954,
            0.20762,
            -2.76642,
            -2.97685,
            -2.50203,
            2.55611,
            -0.33384,
            2.92153,
            -2.86158,
            -1.24452,
            1.21846,
            -0.33367,
            -0.03547,
            -1.20179,
            3.63957,
            -1.71159,
            4.0541,
            -4.48634,
            0.11373,
            2.12419,
            -4.53783,
            -4.262,
            -4.54375,
            3.88436,
            -0.83426,
            0.73954,
            -0.91651,
            -1.68966,
            4.6591,
            -2.89514,
            3.60754,
            1.24807,
            3.97392,
            -3.98377,
            3.21952,
            -4.70175,
            -4.38814,
            -4.0123,
            -4.70817,
            3.03982
        ],
        "var_2": [
            4.41228,
            -1.79245,
            -4.23486,
            -1.71671,
            -1.94282,
            3.57568,
            -2.92219,
            -2.39306,
            -2.07327,
            -0.69325,
            0.39764,
            1.67918,
            -4.41935,
            2.27186,
            -4.81969,
            -4.3502,
            0.27214,
            1.33707,
            -3.2459,
            -4.59853,
            3.80816,
            -4.08831,
            -3.35468,
            3.052,
            -4.91859,
            -3.84324,
            -1.36796,
            0.41105,
            4.23295,
            2.36288,
            3.88585,
            2.82791,
            -1.11324,
            4.22482,
            -2.14318,
            0.43894,
            -4.17082,
            0.82181,
            1.67962,
            2.97001,
            -1.40249,
            1.57937,
            3.27504,
            2.48416,
            -0.84685,
            2.60857,
            -3.68575,
            2.20797,
            4.30627,
            4.32392,
            -3.53274,
            0.66243,
            2.77334,
            -2.40199,
            1.41459,
            3.90886,
            -2.0886,
            -0.38143,
            0.00025,
            4.20018,
            0.04495,
            3.69222,
            2.63375,
            3.90221,
            -4.0801,
            -2.08842,
            2.61235,
            4.93991,
            4.03236,
            1.7988,
            3.03138,
            -3.41005,
            -3.39992,
            4.48469,
            -2.20563,
            -4.07165,
            -0.06651,
            3.81869,
            4.42337,
            -3.17669,
            0.53233,
            0.18829,
            0.48386,
            4.74833,
            3.05452,
            -4.20163,
            -3.79325,
            3.09357,
            -0.56408,
            -2.56028,
            -4.61117,
            2.15797,
            -2.35633,
            3.15588,
            -4.89992,
            -2.41177,
            -2.82557,
            0.37978,
            3.55,
            -1.49586
        ],
        "target": [
            -9.7538,
            1.53029,
            7.94646,
            -8.71139,
            -7.00557,
            -12.56204,
            1.9607,
            -4.31349,
            -7.36684,
            -0.26992,
            0.07865,
            -2.61885,
            20.98815,
            -7.97688,
            -19.79194,
            -20.17023,
            0.05641,
            3.51893,
            1.71283,
            6.49085,
            4.41721,
            -14.29736,
            -10.04284,
            -7.54311,
            10.13796,
            1.74617,
            -1.74625,
            -1.13439,
            -3.27589,
            7.99439,
            -20.06892,
            12.87681,
            3.30202,
            -6.28856,
            -8.65471,
            -1.08082,
            -20.1158,
            -2.98804,
            -2.22033,
            7.9402,
            -2.23431,
            -4.13119,
            -1.28583,
            7.78017,
            3.03908,
            -0.23771,
            17.25779,
            9.24183,
            -2.19769,
            -0.33981,
            -10.74024,
            -2.14054,
            6.19636,
            1.85523,
            7.14765,
            -8.07516,
            -1.07802,
            1.06658,
            -0.00032,
            -8.92371,
            0.0733,
            3.99967,
            6.1933,
            3.77805,
            -19.16083,
            4.72236,
            7.00754,
            13.57256,
            10.5123,
            -1.27249,
            -13.69637,
            6.95052,
            -13.88559,
            -17.48622,
            9.14319,
            -14.31747,
            -0.17506,
            -0.86703,
            -6.54649,
            -11.39375,
            1.07737,
            0.0129,
            -1.81517,
            15.6961,
            5.10736,
            18.83849,
            12.76474,
            12.75035,
            -1.44595,
            -4.04354,
            -16.89645,
            -12.70237,
            -5.07714,
            -13.82966,
            -3.08654,
            5.93228,
            -12.5665,
            1.1915,
            -9.33854,
            3.92711
        ]
    }
}