{
    "formula": "mult(add(gaussian(var_1, N), cosh(var_2, N)), sinh(gaussian(var_0, N), N(N, N)))",
    "formula_human_readable": "((gaussian(var_1)+cosh(var_2))*sinh(gaussian(var_0)))",
    "formula_depth": 4,
    "n_vars": 3,
    "n_consts": 0,
    "n_points": 100,
    "var_bound_dict": {
        "var_0": [
            -5.0,
            5.0
        ],
        "var_1": [
            -5.0,
            5.0
        ],
        "var_2": [
            -5.0,
            5.0
        ]
    },
    "const_value_dict": {},
    "meta_list": [
        "converge_to_zero_var_0",
        "symmetric_var_0",
        "symmetric_var_1",
        "symmetric_var_2"
    ],
    "points": {
        "var_0": [
            -2.68608,
            -2.455,
            -2.04839,
            -0.80958,
            -3.94754,
            -3.22655,
            4.55453,
            3.46273,
            -3.87595,
            2.67022,
            -2.43138,
            3.47393,
            -2.79082,
            -2.68049,
            1.60439,
            -1.43221,
            0.29634,
            -2.21632,
            4.47827,
            -2.76103,
            0.26288,
            -2.22464,
            -2.68524,
            3.74107,
            4.55745,
            -1.35729,
            -1.83615,
            -4.1021,
            -1.44498,
            -4.65636,
            4.05871,
            0.19196,
            2.66349,
            2.17842,
            -1.2255,
            2.88728,
            -3.20921,
            0.26442,
            3.29634,
            2.26087,
            -1.87169,
            2.3395,
            3.90578,
            4.82744,
            -1.37486,
            -1.71447,
            -2.48194,
            -3.86083,
            -3.99546,
            3.29841,
            -4.48061,
            -3.76273,
            -4.95828,
            -4.14148,
            -1.93988,
            -1.10358,
            0.37603,
            2.87833,
            0.55315,
            -1.65508,
            1.90703,
            4.72785,
            -0.19233,
            -4.63818,
            2.97212,
            -4.73899,
            -0.66219,
            -1.69704,
            -2.31451,
            -1.03075,
            0.70709,
            1.49069,
            -2.13885,
            3.17097,
            -2.19584,
            1.63349,
            -3.51183,
            -2.32384,
            3.42798,
            3.01572,
            -2.29882,
            2.92694,
            -3.88626,
            2.73379,
            3.34339,
            -0.4727,
            -0.45054,
            -0.82909,
            3.55846,
            -2.67506,
            2.41479,
            -0.68447,
            4.25883,
            -2.04845,
            -2.09578,
            -2.5456,
            -3.87238,
            -4.57883,
            -2.46083,
            2.10505
        ],
        "var_1": [
            -1.13186,
            -4.6591,
            4.91881,
            -2.13169,
            -4.72711,
            -4.66411,
            -4.48247,
            4.44479,
            4.97862,
            2.15569,
            -4.42121,
            -0.07231,
            -1.3364,
            -4.50807,
            -4.84631,
            2.60155,
            -1.21764,
            -4.58186,
            2.77291,
            -3.24539,
            3.04287,
            -0.05561,
            4.87401,
            -3.27299,
            3.26767,
            -3.03971,
            3.99167,
            2.52452,
            -3.75184,
            4.17201,
            2.006,
            -4.48114,
            -2.51508,
            -1.82691,
            0.916,
            4.83654,
            0.6172,
            -1.03439,
            4.74219,
            -2.08797,
            0.68929,
            -2.86905,
            -4.41658,
            5.08203,
            -1.5325,
            0.68607,
            -4.74512,
            2.22988,
            -3.27702,
            -4.87986,
            3.17909,
            1.6453,
            -1.47495,
            2.49155,
            4.39418,
            3.90686,
            3.14928,
            -1.86292,
            2.15368,
            0.68767,
            2.57448,
            -3.81269,
            2.38849,
            3.18293,
            -0.67747,
            -2.09954,
            4.08525,
            4.55915,
            -1.98584,
            -3.99701,
            3.97762,
            0.53871,
            3.49042,
            0.17406,
            -0.13322,
            1.71423,
            -3.91998,
            -1.07087,
            3.37314,
            -0.97397,
            -3.46972,
            -3.47874,
            4.24698,
            4.72012,
            -0.79995,
            2.93197,
            2.7403,
            -1.28225,
            2.52736,
            -0.98685,
            4.52204,
            -1.32096,
            -0.56546,
            -3.26189,
            2.02193,
            3.85774,
            -0.48851,
            0.49516,
            1.86305,
            -1.08996
        ],
        "var_2": [
            -2.74837,
            3.50304,
            1.19788,
            0.09899,
            -4.49837,
            1.37538,
            4.20754,
            0.00012,
            0.60392,
            -0.52905,
            -3.45226,
            -3.78341,
            -2.51905,
            -1.74022,
            2.14973,
            3.11593,
            -0.82483,
            -0.70878,
            3.10627,
            1.42576,
            -0.2602,
            1.70294,
            4.72564,
            -3.21891,
            2.77709,
            4.25534,
            0.44376,
            -2.96855,
            0.18734,
            2.37239,
            -0.55997,
            4.431,
            4.27541,
            -1.71667,
            4.02076,
            -2.38618,
            -3.53254,
            -4.01822,
            1.75452,
            2.39059,
            3.90309,
            -2.96362,
            -3.16755,
            -3.21204,
            -4.14748,
            -2.15338,
            1.28407,
            -3.8135,
            -1.2799,
            2.33313,
            2.94671,
            -0.77469,
            -3.26139,
            4.02155,
            -4.11071,
            0.10963,
            2.3459,
            -4.66863,
            3.24935,
            -1.52643,
            -4.34157,
            1.3064,
            1.79795,
            -0.89998,
            -4.89014,
            2.21133,
            2.40069,
            5.0311,
            2.52472,
            -1.52085,
            3.8191,
            -5.01634,
            0.17198,
            2.01611,
            -3.79954,
            -4.76586,
            3.16312,
            4.59237,
            -4.14554,
            1.05213,
            -4.08284,
            1.17593,
            -0.54812,
            0.28389,
            -3.32883,
            -3.92454,
            0.32689,
            -2.90132,
            3.08799,
            -3.9653,
            -3.3709,
            0.64187,
            2.71137,
            1.19955,
            4.435,
            3.24236,
            2.01296,
            -3.08706,
            2.06605,
            -4.65863
        ],
        "target": [
            0.06855,
            0.31256,
            0.08543,
            0.29703,
            0.00452,
            0.00362,
            0.00036,
            0.00094,
            0.00024,
            0.01424,
            0.35784,
            0.02673,
            0.04797,
            0.03184,
            0.50004,
            1.57784,
            0.62634,
            0.03786,
            0.0001,
            0.02515,
            0.45232,
            0.13735,
            0.40536,
            0.00632,
            8e-05,
            5.32434,
            0.07073,
            0.00077,
            0.14258,
            6e-05,
            0.0001,
            19.20177,
            0.43488,
            0.11089,
            6.05232,
            0.02971,
            0.03576,
            10.81113,
            0.00472,
            0.15212,
            1.49171,
            0.22186,
            0.00528,
            0.0,
            5.00384,
            0.39662,
            0.03533,
            0.00547,
            0.00033,
            0.00633,
            0.0001,
            0.00037,
            0.0,
            0.00172,
            2.01339,
            0.19582,
            1.97419,
            0.29074,
            4.19813,
            0.25222,
            2.22319,
            2e-05,
            1.16298,
            1e-05,
            0.2035,
            0.0,
            1.83417,
            6.331,
            0.15992,
            0.60495,
            7.97814,
            7.97805,
            0.04071,
            0.00706,
            0.9153,
            6.57991,
            0.00624,
            1.47352,
            0.02525,
            0.01049,
            1.00221,
            0.00765,
            9e-05,
            0.01247,
            0.01977,
            9.63871,
            0.35347,
            2.46491,
            0.00704,
            0.31383,
            0.3564,
            0.42581,
            0.0004,
            0.11098,
            1.89738,
            0.20731,
            0.0014,
            0.00011,
            0.06175,
            2.08476
        ]
    }
}