{
    "formula": "add(add(sqrt(var_1, N), mult(var_0, C_0)), sqrt(sinh(var_2, N), N(N, N)))",
    "formula_human_readable": "((sqrt(var_1)+(var_0*C_0))+sqrt(sinh(var_2)))",
    "formula_depth": 4,
    "n_vars": 3,
    "n_consts": 1,
    "n_points": 100,
    "var_bound_dict": {
        "var_0": [
            -5.0,
            5.0
        ],
        "var_1": [
            -5.0,
            5.0
        ],
        "var_2": [
            -5.0,
            5.0
        ]
    },
    "const_value_dict": {
        "C_0": 0.61496
    },
    "meta_list": [
        "symmetric_var_1",
        "symmetric_var_2"
    ],
    "points": {
        "var_0": [
            1.40373,
            0.93024,
            1.40993,
            2.51152,
            1.0618,
            -3.11524,
            -4.7016,
            -4.07413,
            2.00962,
            3.54394,
            -4.97086,
            -1.18502,
            1.62317,
            4.02727,
            -4.52338,
            1.58182,
            -0.5659,
            -4.10377,
            2.93944,
            2.08669,
            -3.54672,
            2.9627,
            4.13327,
            -3.21744,
            0.79575,
            -3.02079,
            -1.04742,
            -4.25333,
            3.02011,
            -4.98273,
            2.87345,
            -4.42858,
            1.13711,
            1.18322,
            0.50455,
            -3.83395,
            4.97042,
            3.67643,
            -1.48196,
            0.0202,
            -0.12765,
            -0.92868,
            3.13728,
            0.48105,
            -1.69638,
            3.67734,
            1.97649,
            4.18753,
            2.56478,
            -4.69037,
            4.76066,
            1.57604,
            -2.53376,
            -0.93682,
            1.42421,
            -4.29821,
            -0.48187,
            1.96623,
            -4.20929,
            -3.86828,
            2.72774,
            1.21735,
            2.19367,
            1.87828,
            0.59892,
            -4.513,
            -0.65956,
            -1.67883,
            4.09045,
            -0.2394,
            2.63073,
            -2.27187,
            2.24856,
            -1.93869,
            -3.37621,
            3.60933,
            0.92175,
            -0.38089,
            2.26366,
            4.55722,
            3.23516,
            -4.87546,
            0.63885,
            -4.69986,
            -0.34456,
            0.0785,
            -3.27038,
            3.64376,
            -1.98998,
            -3.07052,
            -2.78866,
            -3.91311,
            0.95544,
            3.30962,
            1.83586,
            -2.00079,
            -0.65623,
            -1.69643,
            4.12829,
            -1.46435
        ],
        "var_1": [
            -1.19813,
            -3.36769,
            1.4598,
            -0.46055,
            1.01691,
            2.07371,
            4.28757,
            1.2162,
            -1.18183,
            4.78804,
            2.59641,
            0.73446,
            -0.28508,
            -4.64054,
            2.732,
            1.65449,
            -1.0064,
            -3.55654,
            4.71112,
            -3.16512,
            -4.77992,
            2.85815,
            -1.55833,
            -2.10831,
            0.53176,
            -3.98066,
            3.7983,
            -0.76692,
            1.13239,
            -4.01575,
            0.01846,
            2.75641,
            -4.59599,
            4.46264,
            0.46276,
            -3.02066,
            -0.67063,
            0.93875,
            -4.45908,
            2.19508,
            -2.68245,
            1.69678,
            -3.01856,
            1.02105,
            -0.26613,
            3.08326,
            1.91749,
            3.37296,
            -1.68309,
            -3.72882,
            -4.06954,
            4.61118,
            4.86194,
            -5.18632,
            -0.11582,
            -2.86401,
            1.09228,
            -3.3959,
            -2.47086,
            0.64154,
            0.90223,
            2.78197,
            -2.58695,
            3.76719,
            -1.85864,
            -0.83524,
            3.71251,
            0.9383,
            -4.23588,
            4.75059,
            -1.43349,
            1.77276,
            4.0038,
            -1.59796,
            4.12035,
            0.63987,
            -5.00252,
            -4.20228,
            0.68652,
            3.49458,
            -1.92925,
            0.6092,
            -0.99668,
            -3.64932,
            0.66851,
            1.55265,
            4.04848,
            1.55544,
            4.35859,
            4.20769,
            4.30699,
            -1.47834,
            -4.21345,
            4.45921,
            0.77016,
            -2.87866,
            -3.0632,
            0.59867,
            3.06325,
            -3.55967
        ],
        "var_2": [
            -4.30028,
            1.56415,
            0.14804,
            1.83615,
            0.78393,
            2.75698,
            3.55251,
            -0.4246,
            1.32608,
            1.98172,
            -2.08849,
            3.57928,
            -3.0447,
            2.95597,
            -4.23286,
            -3.9959,
            2.52236,
            1.43695,
            -4.45928,
            3.1713,
            -2.99368,
            3.08114,
            0.50479,
            -4.91874,
            -2.61738,
            3.35004,
            -3.86434,
            4.43991,
            -0.28784,
            -4.11701,
            -4.65926,
            4.48355,
            -3.26746,
            2.99224,
            2.14564,
            -1.11219,
            4.12604,
            0.69678,
            -4.08373,
            -2.83847,
            2.03253,
            -1.47562,
            4.11922,
            1.13174,
            3.65454,
            1.09536,
            0.91568,
            -2.16402,
            -2.72669,
            -4.52938,
            -4.11946,
            3.22196,
            2.44702,
            -4.63618,
            -2.62041,
            2.47199,
            -4.27306,
            -2.10067,
            -2.65868,
            2.66536,
            -0.18603,
            2.87087,
            -2.39461,
            1.96259,
            0.07545,
            3.62642,
            4.56135,
            -4.84758,
            -4.7437,
            4.02586,
            -2.47232,
            2.61647,
            -4.23764,
            -1.08716,
            0.58651,
            -4.92078,
            -4.72967,
            -0.56246,
            2.62936,
            -4.04026,
            -3.71709,
            0.89947,
            -0.32388,
            4.25423,
            0.05086,
            4.35489,
            2.07313,
            2.85118,
            -1.15883,
            2.15007,
            5.11481,
            -0.29744,
            1.08042,
            0.51963,
            1.69455,
            -1.98578,
            -1.39685,
            -1.67113,
            3.2035,
            3.60913
        ],
        "target": [
            8.38788,
            3.43953,
            2.3005,
            4.47706,
            2.48454,
            2.19832,
            3.08291,
            -0.68075,
            4.0495,
            6.30854,
            0.66379,
            4.49615,
            4.58235,
            6.97314,
            4.57292,
            7.42161,
            3.03425,
            0.82914,
            10.38372,
            7.15608,
            2.89231,
            7.02947,
            4.62473,
            7.945,
            3.89631,
            4.29778,
            5.75873,
            4.54575,
            3.58742,
            4.26506,
            9.68141,
            5.885,
            7.02051,
            5.88097,
            3.10068,
            0.53906,
            10.40585,
            4.105,
            6.2053,
            4.35871,
            3.3811,
            2.12276,
            9.31303,
            2.30333,
            3.87713,
            5.37734,
            3.96859,
            5.77911,
            5.59807,
            6.35912,
            10.71983,
            6.75523,
            2.93942,
            8.19648,
            3.71317,
            1.51508,
            6.82865,
            5.40014,
            1.68283,
            1.03466,
            3.2917,
            5.09956,
            5.02404,
            5.08855,
            1.83897,
            2.31542,
            9.24668,
            7.4651,
            12.21259,
            7.08992,
            4.92456,
            2.27088,
            9.15311,
            1.26862,
            0.79028,
            11.2292,
            11.49259,
            2.6275,
            4.58236,
            9.87119,
            7.98413,
            -1.24837,
            2.01232,
            4.79721,
            0.78761,
            7.80061,
            1.97553,
            6.6625,
            2.22233,
            2.17866,
            8.75883,
            -0.66018,
            3.76153,
            4.45668,
            3.47959,
            2.38838,
            2.5728,
            1.47392,
            7.80698,
            5.46205
        ]
    }
}